signate/__init__.py
signate/cli.py
signate/info.py
swagger_client/__init__.py
swagger_client/api_client.py
swagger_client/configuration.py
swagger_client/rest.py
swagger_client/api/__init__.py
swagger_client/api/default_api.py
swagger_client/models/__init__.py
swagger_client/models/competition.py
swagger_client/models/competitions.py
swagger_client/models/download.py
swagger_client/models/downloads.py
swagger_client/models/error.py
swagger_client/models/file.py
swagger_client/models/files.py
swagger_client/models/submission_option.py
swagger_client/models/submission_options.py
swagger_client/models/success.py
tests/error/__init__.py
tests_2/__init__.py
tests_2/mock_api.py
tests_2/test_cli.py
tests_2/error/__init__.py
tests_2/normal/__init__.py
tests_2/normal/test_cli.py
testsig-1.0.0a0.dist-info/METADATA
testsig-1.0.0a0.dist-info/WHEEL
testsig-1.0.0a0.dist-info/entry_points.txt
testsig-1.0.0a0.dist-info/top_level.txt
testsig-1.0.0a0.dist-info/RECORD
